{
  "generated": "2026-03-13T17:57:08.661606+00:00",
  "title": "ORGANVM: One-Person Enterprise Architecture",
  "subtitle": "How AI-conducted automation enables a single director to operate 149 repositories across 8 functional organs",
  "system_stats": {
    "total_repos": 113,
    "organs": 8,
    "flagships": 12,
    "active_repos": 59,
    "ci_enabled": 104,
    "automated_tests": 4015,
    "mcp_tools": 94,
    "cli_commands": 23,
    "ontologia_entities": 121,
    "governance_policies": 6,
    "operational_runbooks": 6,
    "nervous_system_layers": 10
  },
  "promotion_pipeline": {
    "GRADUATED": 54,
    "ARCHIVED": 53,
    "PUBLIC_PROCESS": 4,
    "LOCAL": 1,
    "CANDIDATE": 1
  },
  "organ_distribution": {
    "ORGAN-I": 19,
    "ORGAN-II": 31,
    "ORGAN-III": 29,
    "ORGAN-IV": 11,
    "ORGAN-V": 2,
    "ORGAN-VI": 6,
    "ORGAN-VII": 4,
    "META-ORGANVM": 11
  },
  "tier_distribution": {
    "flagship": 12,
    "standard": 81,
    "infrastructure": 9,
    "archive": 11
  },
  "omega_scorecard": {
    "met": 7,
    "in_progress": 0,
    "not_met": 10,
    "total": 17,
    "met_criteria": [
      1,
      3,
      5,
      6,
      8,
      13,
      17
    ],
    "in_progress_criteria": [],
    "soak_days": 32,
    "soak_complete": true,
    "soak_incidents": 0
  },
  "technical_highlights": [
    {
      "category": "Identity",
      "detail": "121 entities with permanent ULID-based UIDs, temporal naming, event bus"
    },
    {
      "category": "Sensing",
      "detail": "4 concrete sensors (Registry, Soak, CI, Promotion) producing 115+ signals"
    },
    {
      "category": "Inference",
      "detail": "Tension detection (123 tensions), blast radius propagation, entity clustering"
    },
    {
      "category": "Governance",
      "detail": "6 evolution policies with automated evaluation and revision workflow"
    },
    {
      "category": "State",
      "detail": "Daily entity snapshots with drift detection across 106 entities"
    },
    {
      "category": "Testing",
      "detail": "4,015+ tests across 6 packages, autouse fixture blocks production paths"
    },
    {
      "category": "Schema",
      "detail": "9 JSON Schemas validating all system data contracts"
    },
    {
      "category": "Orchestration",
      "detail": "94 MCP tools exposing full system graph to AI assistants"
    }
  ],
  "architecture_principles": [
    "Unidirectional dependency flow: I\u2192II\u2192III, IV orchestrates, V observes",
    "Promotion state machine: LOCAL\u2192CANDIDATE\u2192PUBLIC_PROCESS\u2192GRADUATED\u2192ARCHIVED",
    "AI-conductor model: human directs, AI generates, human reviews",
    "Protocol-based sensing: ontologia defines interfaces, engine implements concrete sensors",
    "Graceful degradation: all bridge modules work with or without ontologia installed"
  ],
  "validation_evidence": {
    "soak_test": "32 consecutive days, 0 incidents (target: 30, complete)",
    "test_coverage": "4,015+ automated tests, 6 test suites",
    "ci_coverage": "107 repos with CI workflows",
    "schema_validation": "9 JSON Schemas with examples",
    "governance_audit": "Automated policy evaluation across all entities",
    "operational_readiness": "6 runbooks + operational handoff guide"
  }
}
